pysloth/__init__.py
pysloth-0.0.3.dist-info/LICENSE
pysloth-0.0.3.dist-info/METADATA
pysloth-0.0.3.dist-info/WHEEL
pysloth-0.0.3.dist-info/top_level.txt
pysloth-0.0.3.dist-info/RECORD
