Metadata-Version: 2.1
Name: pysloth
Version: 0.0.3
Summary: Probabilistic Predictions
Home-page: https://github.com/PySloth/pysloth
Author: PySloth
Author-email: pysloth.python@gmail.com
License: Apache Software License
Platform: UNKNOWN
Classifier: Programming Language :: Python :: 3
Classifier: License :: OSI Approved :: Apache Software License
Classifier: Operating System :: OS Independent
Classifier: Topic :: Scientific/Engineering :: Artificial Intelligence
Classifier: Topic :: Scientific/Engineering :: Mathematics
Requires-Python: >=3.6
Requires-Dist: statsmodels (>=0.12.2)
Requires-Dist: scikit-learn (>=0.24.1)
Requires-Dist: numpy (>=1.19.2)
